mill_utils/__init__.py
mill_utils/utils.py
mill_utils/algorithm/GA.py
mill_utils/algorithm/__init__.py
mill_utils/algorithm/search_list_args.py
mill_utils/dataframe/__init__.py
mill_utils/dataframe/data_description.py
mill_utils/dataframe/main.py
mill_utils/plot/__init__.py
mill_utils/plot/plot_bar.py
plot/__init__.py
plot/utils.py
mill_utils-1.11.dist-info/METADATA
mill_utils-1.11.dist-info/WHEEL
mill_utils-1.11.dist-info/top_level.txt
mill_utils-1.11.dist-info/RECORD
