Metadata-Version: 2.1
Name: mill-utils
Version: 1.11
Summary: Machine learning Toolkit
Home-page: https://gitee.com/mill_teacher/python-mill-utils.git
Author: mill
Author-email: 563084506@qq.com
License: MIT
Platform: UNKNOWN
